svt_text/__init__.py
svt_text/common.py
svt_text/fetch.py
svt_text/generated.py
svt_text/render.py
svt_text/svt_text.py
svt_text/tiles/777-0-10-21.pbm
svt_text/tiles/777-0-11-21.pbm
svt_text/tiles/777-0-11-22.pbm
svt_text/tiles/bott&.pbm
svt_text/tiles/bott(.pbm
svt_text/tiles/bott).pbm
svt_text/tiles/bott*.pbm
"svt_text/tiles/bott,.pbm"
svt_text/tiles/bott-.pbm
svt_text/tiles/bott..pbm
svt_text/tiles/bott0.pbm
svt_text/tiles/bott1.pbm
svt_text/tiles/bott2.pbm
svt_text/tiles/bott4.pbm
svt_text/tiles/bott5.pbm
svt_text/tiles/bott7.pbm
svt_text/tiles/bott9.pbm
svt_text/tiles/bott:.pbm
svt_text/tiles/bott?.pbm
svt_text/tiles/bottA.pbm
svt_text/tiles/bottB.pbm
svt_text/tiles/bottC.pbm
svt_text/tiles/bottD.pbm
svt_text/tiles/bottG.pbm
svt_text/tiles/bottI.pbm
svt_text/tiles/bottJ.pbm
svt_text/tiles/bottK.pbm
svt_text/tiles/bottL.pbm
svt_text/tiles/bottN.pbm
svt_text/tiles/bottO.pbm
svt_text/tiles/bottP.pbm
svt_text/tiles/bottQ.pbm
svt_text/tiles/bottR.pbm
svt_text/tiles/bottS.pbm
svt_text/tiles/bottU.pbm
svt_text/tiles/bottV.pbm
svt_text/tiles/bottW.pbm
svt_text/tiles/bottX.pbm
svt_text/tiles/bottZ.pbm
svt_text/tiles/botta.pbm
svt_text/tiles/bottb.pbm
svt_text/tiles/bottc.pbm
svt_text/tiles/botte.pbm
svt_text/tiles/bottf.pbm
svt_text/tiles/bottg.pbm
svt_text/tiles/botth.pbm
svt_text/tiles/bottj.pbm
svt_text/tiles/bottk.pbm
svt_text/tiles/bottl.pbm
svt_text/tiles/bottm.pbm
svt_text/tiles/bottn.pbm
svt_text/tiles/botto.pbm
svt_text/tiles/bottp.pbm
svt_text/tiles/bottq.pbm
svt_text/tiles/bottr.pbm
svt_text/tiles/botts.pbm
svt_text/tiles/bottt.pbm
svt_text/tiles/bottu.pbm
svt_text/tiles/bottv.pbm
svt_text/tiles/bottw.pbm
svt_text/tiles/bottx.pbm
svt_text/tiles/bottz.pbm
svt_text/tiles/bottÅ.pbm
svt_text/tiles/char .pbm
svt_text/tiles/char!.pbm
"svt_text/tiles/char"".pbm"
svt_text/tiles/char#.pbm
svt_text/tiles/char%.pbm
svt_text/tiles/char&.pbm
svt_text/tiles/char'.pbm
svt_text/tiles/char(.pbm
svt_text/tiles/char).pbm
svt_text/tiles/char*.pbm
svt_text/tiles/char+.pbm
svt_text-0.2.1.dist-info/COPYING
svt_text-0.2.1.dist-info/METADATA
svt_text-0.2.1.dist-info/WHEEL
svt_text-0.2.1.dist-info/entry_points.txt
svt_text-0.2.1.dist-info/top_level.txt
svt_text-0.2.1.dist-info/RECORD
