Metadata-Version: 2.1
Name: svt-text
Version: 0.2.1
Summary: Displays SVT-text in a terminal
Home-page: https://github.com/rickardnorlander/svt-text
Author: Rickard Norlander
Author-email: rickard@rinor.se
Classifier: Programming Language :: Python :: 3
Classifier: License :: OSI Approved :: GNU Affero General Public License v3
Classifier: Operating System :: OS Independent
Requires-Python: >=3.7
License-File: COPYING
Requires-Dist: Pillow
Requires-Dist: numpy
Requires-Dist: requests
